sparc/dataset/__init__.py
sparc/dataset/scaffold.py
sparc_dataset_tools-0.2.5.dist-info/LICENSE
sparc_dataset_tools-0.2.5.dist-info/METADATA
sparc_dataset_tools-0.2.5.dist-info/WHEEL
sparc_dataset_tools-0.2.5.dist-info/entry_points.txt
sparc_dataset_tools-0.2.5.dist-info/top_level.txt
sparc_dataset_tools-0.2.5.dist-info/RECORD
