Metadata-Version: 2.1
Name: sparc-dataset-tools
Version: 0.2.5
Summary: A collection of tools to help with creating SPARC datasets.
Home-page: https://github.com/ABI-Software/sparc-dataset-tools.git
Author: Hugh Sorby
Author-email: h.sorby@auckland.ac.nz
License: Apache Software License
License-File: LICENSE
Requires-Dist: cmlibs.zinc >=3.6.0
Requires-Dist: cmlibs.exporter >=0.3.0
Requires-Dist: scaffoldmaker
Requires-Dist: sparc-curation-tools >=0.7.6
Provides-Extra: test
Requires-Dist: dulwich ; extra == 'test'
